discord_travisbot-0.0.1.dev20170528.dist-info/DESCRIPTION.rst
discord_travisbot-0.0.1.dev20170528.dist-info/METADATA
discord_travisbot-0.0.1.dev20170528.dist-info/RECORD
discord_travisbot-0.0.1.dev20170528.dist-info/WHEEL
discord_travisbot-0.0.1.dev20170528.dist-info/metadata.json
discord_travisbot-0.0.1.dev20170528.dist-info/top_level.txt
travisbot/__init__.py
travisbot/__main__.py
travisbot/api.py
travisbot/bot.py
travisbot/conf.py
travisbot/web.py
