Metadata-Version: 2.0
Name: discord-travisbot
Version: 0.0.1.dev20170528
Summary: Travis bot for Discord.
Home-page: https://github.com/greut/travisbot
Author: Yoan Blanc
Author-email: yoan@dosimple.ch
License: https://opensource.org/licenses/BSD-3-Clause
Keywords: discord asyncio bot
Platform: UNKNOWN
Classifier: Development Status :: 2 - Pre-Alpha
Classifier: Environment :: Console
Classifier: Intended Audience :: Education
Classifier: Operating System :: MacOS :: MacOS X
Classifier: Operating System :: Microsoft :: Windows
Classifier: Operating System :: POSIX
Classifier: Programming Language :: Python :: 3 :: Only
Classifier: Programming Language :: Python :: 3.6
Classifier: Programming Language :: Python :: Implementation :: CPython
Classifier: Topic :: System :: Monitoring
Requires-Python: >=3.6
Requires-Dist: PyOpenSSL (>=17.0.0)
Requires-Dist: aiohttp (>=2.1.0)
Provides-Extra: fast
Requires-Dist: aiodns; extra == 'fast'
Requires-Dist: cchardet; extra == 'fast'
Provides-Extra: qa
Requires-Dist: flake8; extra == 'qa'
Requires-Dist: isort; extra == 'qa'
Requires-Dist: pycodestyle; extra == 'qa'
Requires-Dist: pydocstyle; extra == 'qa'
Requires-Dist: rstcheck; extra == 'qa'
